test/__init__.py
test/test_base_request.py
test/test_base_response.py
test/test_check_api.py
test/test_check_cpu_load_request.py
test/test_check_device_request.py
test/test_check_disk_request.py
test/test_check_hardware_health_request.py
test/test_check_identify_request.py
test/test_check_interface_metrics_request.py
test/test_check_memory_usage_request.py
test/test_check_request.py
test/test_check_response.py
test/test_check_sbc_request.py
test/test_check_server_request.py
test/test_check_snmp_request.py
test/test_check_thola_server_request.py
test/test_check_ups_request.py
test/test_connection_data.py
test/test_cpu_component.py
test/test_device.py
test/test_device_data.py
test/test_disk_component.py
test/test_disk_component_storage.py
test/test_dwdm_interface.py
test/test_ethernet_like_interface.py
test/test_hardware_health_component.py
test/test_hardware_health_component_fan.py
test/test_hardware_health_component_power_supply.py
test/test_http_connection_data.py
test/test_identify_api.py
test/test_identify_request.py
test/test_identify_response.py
test/test_interface.py
test/test_optical_amplifier_interface.py
test/test_optical_channel.py
test/test_optical_opm_interface.py
test/test_optical_transponder_interface.py
test/test_output_error.py
test/test_output_message.py
test/test_performance_data_point.py
test/test_properties.py
test/test_radio_interface.py
test/test_read_api.py
test/test_read_available_components_request.py
test/test_read_available_components_response.py
test/test_read_count_interfaces_request.py
test/test_read_count_interfaces_response.py
test/test_read_cpu_load_request.py
test/test_read_cpu_load_response.py
test/test_read_disk_request.py
test/test_read_disk_response.py
test/test_read_hardware_health_request.py
test/test_read_hardware_health_response.py
test/test_read_interfaces_request.py
test/test_read_interfaces_response.py
test/test_read_memory_usage_request.py
test/test_read_memory_usage_response.py
test/test_read_request.py
thola_client-1.0.2.dist-info/LICENSE
thola_client-1.0.2.dist-info/METADATA
thola_client-1.0.2.dist-info/WHEEL
thola_client-1.0.2.dist-info/top_level.txt
thola_client-1.0.2.dist-info/RECORD
