Metadata-Version: 2.1
Name: thola-client
Version: 1.0.2
Summary: Thola
Home-page: UNKNOWN
Author-email: 
License: UNKNOWN
Keywords: Thola,Client
Platform: UNKNOWN
Requires-Dist: certifi (>=2017.4.17)
Requires-Dist: python-dateutil (>=2.1)
Requires-Dist: six (>=1.10)
Requires-Dist: urllib3 (>=1.23)
